CHANGES.txt
COPYING.txt
README.txt
buildout.cfg
setup.py
bootstrap/bootstrap.py
src/ulif/__init__.py
src/ulif.rest.egg-info/PKG-INFO
src/ulif.rest.egg-info/SOURCES.txt
src/ulif.rest.egg-info/dependency_links.txt
src/ulif.rest.egg-info/namespace_packages.txt
src/ulif.rest.egg-info/not-zip-safe
src/ulif.rest.egg-info/requires.txt
src/ulif.rest.egg-info/top_level.txt
src/ulif/rest/README.txt
src/ulif/rest/USAGE.txt
src/ulif/rest/__init__.py
src/ulif/rest/directives_plain.py
src/ulif/rest/pygments_directive.py
src/ulif/rest/roles_plain.py
src/ulif/rest/tests/DocutilsTestSupport.py
src/ulif/rest/tests/__init__.py
src/ulif/rest/tests/alltests.py
src/ulif/rest/tests/docutils_difflib.py
src/ulif/rest/tests/package_unittest.py
src/ulif/rest/tests/test_directives/__init__.py
src/ulif/rest/tests/test_directives/test_data.py
src/ulif/rest/tests/test_directives/test_function.py
src/ulif/rest/tests/test_directives/test_seealso.py
src/ulif/rest/tests/test_directives/test_toctree.py
src/ulif/rest/tests/test_directives/test_version.py
