Metadata-Version: 1.0
Name: ulif.rest
Version: 0.1.0
Summary: ReStructuredText extensions.
Home-page: http://pypi.python.org/pypi/ulif.rest
Author: Uli Fouquet, parts by Georg Brandl and Lea Wiemann
Author-email: uli@gnufix.de
License: public domain, BSD, GPL
Keywords: docutils sphinx documentation rest restructuredtext pygments
Platform: UNKNOWN
Classifier: Development Status :: 3 - Alpha
Classifier: Environment :: Console
Classifier: Intended Audience :: Developers
Classifier: Intended Audience :: End Users/Desktop
Classifier: Intended Audience :: Other Audience
Classifier: Intended Audience :: System Administrators
Classifier: License :: OSI Approved :: BSD License
Classifier: License :: OSI Approved :: GNU General Public License (GPL)
Classifier: License :: Public Domain
Classifier: Programming Language :: Python
Classifier: Operating System :: OS Independent
Classifier: Topic :: Documentation
Classifier: Topic :: Software Development :: Documentation
Classifier: Topic :: Text Processing
